faker_maytok_food/__init__.py
faker_maytok_food/dish_descriptions.py
faker_maytok_food/dishes.py
faker_maytok_food/ethnic_categories.py
faker_maytok_food/fruits.py
faker_maytok_food/ingredients.py
faker_maytok_food/measurements.py
faker_maytok_food/spices.py
faker_maytok_food/sushi.py
faker_maytok_food/vegetables.py
faker_maytok_food-0.1.0.dist-info/LICENSE
faker_maytok_food-0.1.0.dist-info/METADATA
faker_maytok_food-0.1.0.dist-info/WHEEL
faker_maytok_food-0.1.0.dist-info/RECORD
