Metadata-Version: 2.3
Name: faker_maytok_food
Version: 0.1.0
Summary: Food related provider for the Python Faker library
License: MIT
Keywords: faker,data,test,mock,generator,food
Author: Giancarlo Ventura
Author-email: giancarlo@maytok.com
Requires-Python: >=3.8
Classifier: Intended Audience :: Developers
Classifier: License :: OSI Approved :: MIT License
Classifier: Programming Language :: Python
Classifier: Programming Language :: Python :: 3
Classifier: Programming Language :: Python :: 3.8
Classifier: Programming Language :: Python :: 3.9
Classifier: Programming Language :: Python :: 3.10
Classifier: Programming Language :: Python :: 3.11
Classifier: Programming Language :: Python :: 3.12
Classifier: Programming Language :: Python :: 3.13
Classifier: Topic :: Software Development
Classifier: Topic :: Software Development :: Libraries :: Python Modules
Classifier: Topic :: Software Development :: Testing
Requires-Dist: Faker (>=12.0.0)
Project-URL: Homepage, https://github.com/khanmaytok/faker_maytok_food
Project-URL: Repository, https://github.com/khanmaytok/faker_maytok_food
